LICENSE
README.md
setup.py
sangreal_calendar/__init__.py
sangreal_calendar/utils.py
sangreal_calendar.egg-info/PKG-INFO
sangreal_calendar.egg-info/SOURCES.txt
sangreal_calendar.egg-info/dependency_links.txt
sangreal_calendar.egg-info/requires.txt
sangreal_calendar.egg-info/top_level.txt
sangreal_calendar/core/__init__.py
sangreal_calendar/core/refresh_rate_handle.py
sangreal_calendar/core/trade_dt_futures.py
sangreal_calendar/core/trade_dt_handle.py